{
  "packSlug": "m1l",
  "points": [
    {
      "date": "2026-06-15",
      "prices": {
        "m1l-091-063-sar": 36800
      }
    },
    {
      "date": "2026-06-18",
      "prices": {
        "m1l-001-063-c": 79,
        "m1l-002-063-c": 37,
        "m1l-003-063-rr": 180,
        "m1l-004-063-c": 160,
        "m1l-005-063-u": 160,
        "m1l-006-063-u": 160,
        "m1l-007-063-c": 160,
        "m1l-008-063-c": 160,
        "m1l-009-063-u": 160,
        "m1l-010-063-c": 160,
        "m1l-011-063-u": 160,
        "m1l-012-063-c": 160,
        "m1l-013-063-rr": 160,
        "m1l-014-063-u": 160,
        "m1l-015-063-c": 160,
        "m1l-016-063-c": 160,
        "m1l-018-063-c": 160,
        "m1l-019-063-c": 160,
        "m1l-020-063-c": 160,
        "m1l-021-063-c": 160,
        "m1l-022-063-c": 160,
        "m1l-023-063-c": 160,
        "m1l-024-063-c": 160,
        "m1l-025-063-r": 159,
        "m1l-026-063-r": 160,
        "m1l-027-063-u": 37,
        "m1l-028-063-c": 19,
        "m1l-029-063-rr": 180,
        "m1l-030-063-c": 160,
        "m1l-031-063-c": 160,
        "m1l-032-063-u": 160,
        "m1l-033-063-u": 160,
        "m1l-034-063-c": 160,
        "m1l-035-063-c": 160,
        "m1l-036-063-u": 160,
        "m1l-037-063-u": 160,
        "m1l-038-063-rr": 80,
        "m1l-039-063-u": 160,
        "m1l-040-063-r": 90,
        "m1l-041-063-c": 160,
        "m1l-042-063-c": 160,
        "m1l-043-063-c": 160,
        "m1l-044-063-c": 160,
        "m1l-045-063-r": 160,
        "m1l-046-063-rr": 160,
        "m1l-047-063-r": 160,
        "m1l-048-063-c": 160,
        "m1l-049-063-c": 160,
        "m1l-050-063-u": 160,
        "m1l-051-063-u": 160,
        "m1l-052-063-c": 160,
        "m1l-053-063-c": 160,
        "m1l-054-063-c": 160,
        "m1l-055-063-c": 160,
        "m1l-056-063-u": 160,
        "m1l-057-063-u": 19,
        "m1l-058-063-u": 47,
        "m1l-059-063-u": 60,
        "m1l-060-063-u": 160,
        "m1l-061-063-u": 160,
        "m1l-062-063-u": 100,
        "m1l-063-063-u": 60,
        "m1l-064-063-ar": 1480,
        "m1l-065-063-ar": 520,
        "m1l-066-063-ar": 230,
        "m1l-067-063-ar": 350,
        "m1l-068-063-ar": 580,
        "m1l-069-063-ar": 480,
        "m1l-070-063-ar": 380,
        "m1l-071-063-ar": 230,
        "m1l-072-063-ar": 230,
        "m1l-073-063-ar": 290,
        "m1l-074-063-ar": 380,
        "m1l-075-063-ar": 380,
        "m1l-076-063-sr": 1280,
        "m1l-077-063-sr": 230,
        "m1l-078-063-sr": 1680,
        "m1l-079-063-sr": 780,
        "m1l-080-063-sr": 480,
        "m1l-081-063-sr": 380,
        "m1l-082-063-sr": 280,
        "m1l-083-063-sr": 280,
        "m1l-084-063-sr": 280,
        "m1l-085-063-sr": 380,
        "m1l-086-063-sr": 9980,
        "m1l-087-063-sar": 7480,
        "m1l-088-063-sar": 10200,
        "m1l-089-063-sar": 3980,
        "m1l-090-063-sar": 980,
        "m1l-091-063-sar": 36800,
        "m1l-092-063-mur": 63980
      }
    },
    {
      "date": "2026-07-04",
      "prices": {
        "m1l-001-063-c": 79,
        "m1l-002-063-c": 37,
        "m1l-003-063-rr": 180,
        "m1l-004-063-c": 160,
        "m1l-005-063-u": 160,
        "m1l-006-063-u": 160,
        "m1l-007-063-c": 160,
        "m1l-008-063-c": 160,
        "m1l-009-063-u": 160,
        "m1l-010-063-c": 160,
        "m1l-011-063-u": 160,
        "m1l-012-063-c": 160,
        "m1l-013-063-rr": 160,
        "m1l-014-063-u": 160,
        "m1l-015-063-c": 160,
        "m1l-016-063-c": 160,
        "m1l-018-063-c": 160,
        "m1l-019-063-c": 160,
        "m1l-020-063-c": 160,
        "m1l-021-063-c": 160,
        "m1l-022-063-c": 160,
        "m1l-023-063-c": 160,
        "m1l-024-063-c": 160,
        "m1l-025-063-r": 159,
        "m1l-026-063-r": 160,
        "m1l-027-063-u": 37,
        "m1l-028-063-c": 19,
        "m1l-029-063-rr": 180,
        "m1l-030-063-c": 160,
        "m1l-031-063-c": 160,
        "m1l-032-063-u": 160,
        "m1l-033-063-u": 160,
        "m1l-034-063-c": 160,
        "m1l-035-063-c": 160,
        "m1l-036-063-u": 160,
        "m1l-037-063-u": 160,
        "m1l-038-063-rr": 89,
        "m1l-039-063-u": 160,
        "m1l-041-063-c": 160,
        "m1l-042-063-c": 160,
        "m1l-043-063-c": 160,
        "m1l-044-063-c": 160,
        "m1l-045-063-r": 160,
        "m1l-046-063-rr": 160,
        "m1l-047-063-r": 160,
        "m1l-048-063-c": 160,
        "m1l-049-063-c": 160,
        "m1l-050-063-u": 160,
        "m1l-051-063-u": 160,
        "m1l-052-063-c": 160,
        "m1l-053-063-c": 160,
        "m1l-054-063-c": 160,
        "m1l-055-063-c": 160,
        "m1l-056-063-u": 160,
        "m1l-057-063-u": 19,
        "m1l-058-063-u": 40,
        "m1l-059-063-u": 100,
        "m1l-060-063-u": 160,
        "m1l-061-063-u": 160,
        "m1l-062-063-u": 160,
        "m1l-063-063-u": 30,
        "m1l-064-063-ar": 1480,
        "m1l-065-063-ar": 590,
        "m1l-066-063-ar": 380,
        "m1l-067-063-ar": 580,
        "m1l-068-063-ar": 580,
        "m1l-069-063-ar": 480,
        "m1l-070-063-ar": 340,
        "m1l-071-063-ar": 340,
        "m1l-072-063-ar": 340,
        "m1l-073-063-ar": 480,
        "m1l-074-063-ar": 270,
        "m1l-075-063-ar": 340,
        "m1l-076-063-sr": 1280,
        "m1l-077-063-sr": 290,
        "m1l-078-063-sr": 1480,
        "m1l-079-063-sr": 780,
        "m1l-080-063-sr": 480,
        "m1l-081-063-sr": 380,
        "m1l-082-063-sr": 280,
        "m1l-083-063-sr": 280,
        "m1l-084-063-sr": 280,
        "m1l-085-063-sr": 380,
        "m1l-086-063-sr": 8980,
        "m1l-088-063-sar": 12800,
        "m1l-089-063-sar": 3480,
        "m1l-090-063-sar": 980,
        "m1l-091-063-sar": 32800,
        "m1l-092-063-mur": 65290
      }
    },
    {
      "date": "2026-07-06",
      "prices": {
        "m1l-001-063-c": 79,
        "m1l-002-063-c": 37,
        "m1l-003-063-rr": 180,
        "m1l-004-063-c": 160,
        "m1l-005-063-u": 160,
        "m1l-006-063-u": 160,
        "m1l-007-063-c": 160,
        "m1l-008-063-c": 160,
        "m1l-009-063-u": 160,
        "m1l-010-063-c": 160,
        "m1l-011-063-u": 160,
        "m1l-012-063-c": 160,
        "m1l-013-063-rr": 160,
        "m1l-014-063-u": 160,
        "m1l-015-063-c": 160,
        "m1l-016-063-c": 160,
        "m1l-018-063-c": 160,
        "m1l-019-063-c": 160,
        "m1l-020-063-c": 160,
        "m1l-021-063-c": 160,
        "m1l-022-063-c": 160,
        "m1l-023-063-c": 160,
        "m1l-024-063-c": 160,
        "m1l-025-063-r": 159,
        "m1l-026-063-r": 160,
        "m1l-027-063-u": 37,
        "m1l-028-063-c": 19,
        "m1l-029-063-rr": 180,
        "m1l-030-063-c": 160,
        "m1l-031-063-c": 160,
        "m1l-032-063-u": 160,
        "m1l-033-063-u": 160,
        "m1l-034-063-c": 160,
        "m1l-035-063-c": 160,
        "m1l-036-063-u": 160,
        "m1l-037-063-u": 160,
        "m1l-038-063-rr": 80,
        "m1l-039-063-u": 160,
        "m1l-040-063-r": 90,
        "m1l-041-063-c": 160,
        "m1l-042-063-c": 160,
        "m1l-043-063-c": 160,
        "m1l-044-063-c": 160,
        "m1l-045-063-r": 160,
        "m1l-046-063-rr": 160,
        "m1l-047-063-r": 160,
        "m1l-048-063-c": 160,
        "m1l-049-063-c": 160,
        "m1l-050-063-u": 160,
        "m1l-051-063-u": 160,
        "m1l-052-063-c": 160,
        "m1l-053-063-c": 160,
        "m1l-054-063-c": 160,
        "m1l-055-063-c": 160,
        "m1l-056-063-u": 160,
        "m1l-057-063-u": 19,
        "m1l-058-063-u": 40,
        "m1l-059-063-u": 60,
        "m1l-060-063-u": 160,
        "m1l-061-063-u": 160,
        "m1l-062-063-u": 160,
        "m1l-063-063-u": 30,
        "m1l-064-063-ar": 1480,
        "m1l-065-063-ar": 590,
        "m1l-066-063-ar": 380,
        "m1l-067-063-ar": 580,
        "m1l-068-063-ar": 580,
        "m1l-069-063-ar": 480,
        "m1l-070-063-ar": 380,
        "m1l-071-063-ar": 380,
        "m1l-072-063-ar": 380,
        "m1l-073-063-ar": 480,
        "m1l-074-063-ar": 300,
        "m1l-075-063-ar": 380,
        "m1l-076-063-sr": 1280,
        "m1l-077-063-sr": 290,
        "m1l-078-063-sr": 1480,
        "m1l-079-063-sr": 780,
        "m1l-080-063-sr": 480,
        "m1l-081-063-sr": 380,
        "m1l-082-063-sr": 280,
        "m1l-083-063-sr": 280,
        "m1l-084-063-sr": 280,
        "m1l-085-063-sr": 380,
        "m1l-086-063-sr": 8980,
        "m1l-088-063-sar": 12800,
        "m1l-089-063-sar": 3480,
        "m1l-090-063-sar": 980,
        "m1l-091-063-sar": 32800,
        "m1l-092-063-mur": 59800
      }
    },
    {
      "date": "2026-07-07",
      "prices": {
        "m1l-001-063-c": 79,
        "m1l-002-063-c": 37,
        "m1l-003-063-rr": 180,
        "m1l-004-063-c": 160,
        "m1l-005-063-u": 160,
        "m1l-006-063-u": 160,
        "m1l-007-063-c": 160,
        "m1l-008-063-c": 160,
        "m1l-009-063-u": 160,
        "m1l-011-063-u": 160,
        "m1l-012-063-c": 160,
        "m1l-013-063-rr": 160,
        "m1l-014-063-u": 160,
        "m1l-015-063-c": 160,
        "m1l-016-063-c": 160,
        "m1l-018-063-c": 160,
        "m1l-019-063-c": 160,
        "m1l-020-063-c": 160,
        "m1l-021-063-c": 160,
        "m1l-022-063-c": 160,
        "m1l-023-063-c": 160,
        "m1l-024-063-c": 160,
        "m1l-025-063-r": 159,
        "m1l-027-063-u": 37,
        "m1l-028-063-c": 19,
        "m1l-029-063-rr": 180,
        "m1l-030-063-c": 160,
        "m1l-031-063-c": 160,
        "m1l-032-063-u": 160,
        "m1l-033-063-u": 160,
        "m1l-034-063-c": 160,
        "m1l-035-063-c": 160,
        "m1l-036-063-u": 160,
        "m1l-037-063-u": 160,
        "m1l-038-063-rr": 80,
        "m1l-039-063-u": 160,
        "m1l-040-063-r": 90,
        "m1l-042-063-c": 160,
        "m1l-043-063-c": 160,
        "m1l-044-063-c": 160,
        "m1l-045-063-r": 160,
        "m1l-046-063-rr": 160,
        "m1l-047-063-r": 160,
        "m1l-048-063-c": 160,
        "m1l-049-063-c": 160,
        "m1l-050-063-u": 160,
        "m1l-051-063-u": 160,
        "m1l-052-063-c": 160,
        "m1l-053-063-c": 160,
        "m1l-054-063-c": 160,
        "m1l-055-063-c": 160,
        "m1l-056-063-u": 160,
        "m1l-057-063-u": 19,
        "m1l-058-063-u": 40,
        "m1l-059-063-u": 60,
        "m1l-060-063-u": 160,
        "m1l-061-063-u": 160,
        "m1l-062-063-u": 160,
        "m1l-063-063-u": 30,
        "m1l-064-063-ar": 1480,
        "m1l-065-063-ar": 590,
        "m1l-066-063-ar": 380,
        "m1l-067-063-ar": 580,
        "m1l-068-063-ar": 580,
        "m1l-069-063-ar": 480,
        "m1l-070-063-ar": 380,
        "m1l-071-063-ar": 380,
        "m1l-072-063-ar": 380,
        "m1l-073-063-ar": 480,
        "m1l-074-063-ar": 300,
        "m1l-075-063-ar": 380,
        "m1l-076-063-sr": 1280,
        "m1l-077-063-sr": 290,
        "m1l-078-063-sr": 1480,
        "m1l-079-063-sr": 780,
        "m1l-080-063-sr": 480,
        "m1l-081-063-sr": 380,
        "m1l-082-063-sr": 280,
        "m1l-083-063-sr": 280,
        "m1l-084-063-sr": 280,
        "m1l-085-063-sr": 380,
        "m1l-086-063-sr": 8980,
        "m1l-088-063-sar": 12800,
        "m1l-089-063-sar": 3480,
        "m1l-090-063-sar": 980,
        "m1l-091-063-sar": 32800,
        "m1l-092-063-mur": 59800
      }
    },
    {
      "date": "2026-07-08",
      "prices": {
        "m1l-001-063-c": 79,
        "m1l-002-063-c": 37,
        "m1l-003-063-rr": 180,
        "m1l-004-063-c": 160,
        "m1l-005-063-u": 160,
        "m1l-006-063-u": 160,
        "m1l-007-063-c": 160,
        "m1l-008-063-c": 160,
        "m1l-009-063-u": 160,
        "m1l-010-063-c": 160,
        "m1l-011-063-u": 160,
        "m1l-012-063-c": 160,
        "m1l-013-063-rr": 160,
        "m1l-014-063-u": 160,
        "m1l-015-063-c": 160,
        "m1l-016-063-c": 160,
        "m1l-018-063-c": 160,
        "m1l-019-063-c": 160,
        "m1l-020-063-c": 160,
        "m1l-021-063-c": 160,
        "m1l-022-063-c": 160,
        "m1l-023-063-c": 160,
        "m1l-024-063-c": 160,
        "m1l-025-063-r": 159,
        "m1l-026-063-r": 160,
        "m1l-027-063-u": 37,
        "m1l-028-063-c": 19,
        "m1l-029-063-rr": 180,
        "m1l-030-063-c": 160,
        "m1l-031-063-c": 160,
        "m1l-032-063-u": 160,
        "m1l-033-063-u": 160,
        "m1l-034-063-c": 160,
        "m1l-035-063-c": 160,
        "m1l-036-063-u": 160,
        "m1l-037-063-u": 160,
        "m1l-038-063-rr": 89,
        "m1l-039-063-u": 160,
        "m1l-041-063-c": 160,
        "m1l-042-063-c": 160,
        "m1l-043-063-c": 160,
        "m1l-044-063-c": 160,
        "m1l-045-063-r": 160,
        "m1l-046-063-rr": 160,
        "m1l-047-063-r": 160,
        "m1l-048-063-c": 160,
        "m1l-049-063-c": 160,
        "m1l-050-063-u": 160,
        "m1l-051-063-u": 160,
        "m1l-052-063-c": 160,
        "m1l-053-063-c": 160,
        "m1l-054-063-c": 160,
        "m1l-055-063-c": 160,
        "m1l-056-063-u": 160,
        "m1l-057-063-u": 19,
        "m1l-058-063-u": 40,
        "m1l-059-063-u": 100,
        "m1l-060-063-u": 160,
        "m1l-061-063-u": 160,
        "m1l-062-063-u": 160,
        "m1l-063-063-u": 30,
        "m1l-064-063-ar": 1480,
        "m1l-065-063-ar": 590,
        "m1l-066-063-ar": 380,
        "m1l-067-063-ar": 580,
        "m1l-068-063-ar": 580,
        "m1l-069-063-ar": 480,
        "m1l-070-063-ar": 380,
        "m1l-071-063-ar": 380,
        "m1l-072-063-ar": 380,
        "m1l-073-063-ar": 480,
        "m1l-074-063-ar": 300,
        "m1l-075-063-ar": 380,
        "m1l-076-063-sr": 1280,
        "m1l-077-063-sr": 290,
        "m1l-078-063-sr": 1480,
        "m1l-079-063-sr": 780,
        "m1l-080-063-sr": 480,
        "m1l-081-063-sr": 380,
        "m1l-082-063-sr": 280,
        "m1l-083-063-sr": 280,
        "m1l-084-063-sr": 280,
        "m1l-085-063-sr": 380,
        "m1l-086-063-sr": 8980,
        "m1l-088-063-sar": 12800,
        "m1l-089-063-sar": 3480,
        "m1l-090-063-sar": 980,
        "m1l-091-063-sar": 32800,
        "m1l-092-063-mur": 59200
      }
    }
  ]
}
