{
  "packSlug": "sv6a",
  "points": [
    {
      "date": "2026-06-18",
      "prices": {
        "sv6a-001-064-c": 160,
        "sv6a-002-064-u": 18,
        "sv6a-003-064-c": 19,
        "sv6a-004-064-c": 160,
        "sv6a-005-064-u": 19,
        "sv6a-006-064-r": 160,
        "sv6a-007-064-c": 160,
        "sv6a-008-064-c": 160,
        "sv6a-009-064-u": 160,
        "sv6a-010-064-c": 160,
        "sv6a-011-064-c": 160,
        "sv6a-012-064-rr": 160,
        "sv6a-013-064-c": 160,
        "sv6a-014-064-u": 160,
        "sv6a-015-064-rr": 160,
        "sv6a-016-064-c": 160,
        "sv6a-017-064-u": 160,
        "sv6a-018-064-c": 160,
        "sv6a-019-064-c": 160,
        "sv6a-020-064-r": 160,
        "sv6a-021-064-r": 160,
        "sv6a-022-064-u": 19,
        "sv6a-023-064-c": 160,
        "sv6a-024-064-c": 160,
        "sv6a-025-064-r": 160,
        "sv6a-026-064-u": 160,
        "sv6a-027-064-c": 160,
        "sv6a-028-064-c": 160,
        "sv6a-029-064-u": 160,
        "sv6a-030-064-c": 160,
        "sv6a-031-064-c": 160,
        "sv6a-032-064-r": 160,
        "sv6a-033-064-c": 160,
        "sv6a-034-064-u": 160,
        "sv6a-035-064-u": 160,
        "sv6a-036-064-rr": 160,
        "sv6a-037-064-rr": 160,
        "sv6a-038-064-rr": 180,
        "sv6a-039-064-rr": 160,
        "sv6a-040-064-u": 37,
        "sv6a-041-064-c": 160,
        "sv6a-042-064-r": 160,
        "sv6a-043-064-c": 160,
        "sv6a-044-064-c": 160,
        "sv6a-045-064-c": 160,
        "sv6a-046-064-r": 35,
        "sv6a-047-064-u": 160,
        "sv6a-048-064-c": 160,
        "sv6a-049-064-c": 160,
        "sv6a-051-064-c": 160,
        "sv6a-052-064-c": 160,
        "sv6a-053-064-c": 160,
        "sv6a-054-064-ace": 160,
        "sv6a-055-064-ace": 160,
        "sv6a-056-064-u": 160,
        "sv6a-057-064-u": 34,
        "sv6a-058-064-u": 90,
        "sv6a-059-064-u": 94,
        "sv6a-060-064-u": 160,
        "sv6a-062-064-u": 160,
        "sv6a-063-064-ace": 160,
        "sv6a-064-064-u": 50,
        "sv6a-065-064-ar": 380,
        "sv6a-066-064-ar": 590,
        "sv6a-067-064-ar": 780,
        "sv6a-068-064-ar": 880,
        "sv6a-069-064-ar": 980,
        "sv6a-070-064-ar": 980,
        "sv6a-071-064-ar": 480,
        "sv6a-072-064-ar": 680,
        "sv6a-073-064-ar": 480,
        "sv6a-074-064-ar": 480,
        "sv6a-075-064-ar": 1280,
        "sv6a-076-064-ar": 480,
        "sv6a-077-064-sr": 320,
        "sv6a-078-064-sr": 380,
        "sv6a-079-064-sr": 380,
        "sv6a-080-064-sr": 380,
        "sv6a-081-064-sr": 1580,
        "sv6a-082-064-sr": 480,
        "sv6a-083-064-sr": 980,
        "sv6a-084-064-sr": 780,
        "sv6a-085-064-sr": 680,
        "sv6a-086-064-sr": 230,
        "sv6a-087-064-sar": 800,
        "sv6a-088-064-sar": 1080,
        "sv6a-089-064-sar": 4280,
        "sv6a-090-064-sar": 940,
        "sv6a-091-064-sar": 3280,
        "sv6a-092-064-ur": 780,
        "sv6a-093-064-ur": 980,
        "sv6a-094-064-ur": 686
      }
    },
    {
      "date": "2026-07-04",
      "prices": {
        "sv6a-001-064-c": 160,
        "sv6a-002-064-u": 18,
        "sv6a-003-064-c": 19,
        "sv6a-004-064-c": 160,
        "sv6a-005-064-u": 19,
        "sv6a-006-064-r": 160,
        "sv6a-007-064-c": 160,
        "sv6a-008-064-c": 160,
        "sv6a-009-064-u": 160,
        "sv6a-010-064-c": 160,
        "sv6a-011-064-c": 160,
        "sv6a-012-064-rr": 160,
        "sv6a-013-064-c": 160,
        "sv6a-014-064-u": 160,
        "sv6a-015-064-rr": 160,
        "sv6a-016-064-c": 160,
        "sv6a-017-064-u": 160,
        "sv6a-018-064-c": 160,
        "sv6a-019-064-c": 160,
        "sv6a-020-064-r": 160,
        "sv6a-021-064-r": 160,
        "sv6a-022-064-u": 19,
        "sv6a-023-064-c": 160,
        "sv6a-024-064-c": 160,
        "sv6a-025-064-r": 160,
        "sv6a-026-064-u": 160,
        "sv6a-027-064-c": 160,
        "sv6a-028-064-c": 160,
        "sv6a-029-064-u": 160,
        "sv6a-030-064-c": 160,
        "sv6a-031-064-c": 160,
        "sv6a-032-064-r": 160,
        "sv6a-033-064-c": 160,
        "sv6a-034-064-u": 160,
        "sv6a-035-064-u": 160,
        "sv6a-036-064-rr": 160,
        "sv6a-037-064-rr": 160,
        "sv6a-038-064-rr": 180,
        "sv6a-039-064-rr": 160,
        "sv6a-040-064-u": 35,
        "sv6a-041-064-c": 160,
        "sv6a-042-064-r": 35,
        "sv6a-043-064-c": 160,
        "sv6a-044-064-c": 160,
        "sv6a-045-064-c": 160,
        "sv6a-046-064-r": 35,
        "sv6a-047-064-u": 160,
        "sv6a-048-064-c": 160,
        "sv6a-049-064-c": 160,
        "sv6a-050-064-c": 18,
        "sv6a-051-064-c": 160,
        "sv6a-052-064-c": 160,
        "sv6a-053-064-c": 160,
        "sv6a-054-064-ace": 160,
        "sv6a-055-064-ace": 160,
        "sv6a-056-064-u": 110,
        "sv6a-057-064-u": 33,
        "sv6a-058-064-u": 150,
        "sv6a-059-064-u": 99,
        "sv6a-060-064-u": 160,
        "sv6a-062-064-u": 160,
        "sv6a-063-064-ace": 160,
        "sv6a-064-064-u": 50,
        "sv6a-065-064-ar": 340,
        "sv6a-066-064-ar": 590,
        "sv6a-067-064-ar": 780,
        "sv6a-068-064-ar": 880,
        "sv6a-069-064-ar": 980,
        "sv6a-070-064-ar": 980,
        "sv6a-071-064-ar": 480,
        "sv6a-072-064-ar": 680,
        "sv6a-073-064-ar": 480,
        "sv6a-074-064-ar": 480,
        "sv6a-075-064-ar": 1280,
        "sv6a-076-064-ar": 430,
        "sv6a-077-064-sr": 480,
        "sv6a-078-064-sr": 380,
        "sv6a-079-064-sr": 380,
        "sv6a-080-064-sr": 380,
        "sv6a-081-064-sr": 1580,
        "sv6a-082-064-sr": 480,
        "sv6a-083-064-sr": 980,
        "sv6a-084-064-sr": 780,
        "sv6a-085-064-sr": 680,
        "sv6a-086-064-sr": 300,
        "sv6a-087-064-sar": 980,
        "sv6a-088-064-sar": 1080,
        "sv6a-089-064-sar": 4280,
        "sv6a-090-064-sar": 930,
        "sv6a-091-064-sar": 3280,
        "sv6a-092-064-ur": 780,
        "sv6a-093-064-ur": 980,
        "sv6a-094-064-ur": 920
      }
    },
    {
      "date": "2026-07-06",
      "prices": {
        "sv6a-001-064-c": 160,
        "sv6a-002-064-u": 18,
        "sv6a-003-064-c": 19,
        "sv6a-004-064-c": 160,
        "sv6a-005-064-u": 19,
        "sv6a-006-064-r": 160,
        "sv6a-007-064-c": 160,
        "sv6a-008-064-c": 160,
        "sv6a-009-064-u": 160,
        "sv6a-010-064-c": 160,
        "sv6a-011-064-c": 160,
        "sv6a-012-064-rr": 160,
        "sv6a-013-064-c": 160,
        "sv6a-014-064-u": 160,
        "sv6a-015-064-rr": 160,
        "sv6a-016-064-c": 160,
        "sv6a-017-064-u": 160,
        "sv6a-018-064-c": 160,
        "sv6a-019-064-c": 160,
        "sv6a-020-064-r": 160,
        "sv6a-021-064-r": 160,
        "sv6a-022-064-u": 19,
        "sv6a-023-064-c": 160,
        "sv6a-024-064-c": 160,
        "sv6a-025-064-r": 160,
        "sv6a-026-064-u": 160,
        "sv6a-027-064-c": 160,
        "sv6a-028-064-c": 160,
        "sv6a-029-064-u": 160,
        "sv6a-030-064-c": 160,
        "sv6a-031-064-c": 160,
        "sv6a-032-064-r": 160,
        "sv6a-033-064-c": 160,
        "sv6a-034-064-u": 160,
        "sv6a-035-064-u": 160,
        "sv6a-036-064-rr": 160,
        "sv6a-037-064-rr": 160,
        "sv6a-038-064-rr": 180,
        "sv6a-039-064-rr": 160,
        "sv6a-040-064-u": 35,
        "sv6a-041-064-c": 160,
        "sv6a-042-064-r": 35,
        "sv6a-043-064-c": 160,
        "sv6a-044-064-c": 160,
        "sv6a-045-064-c": 160,
        "sv6a-046-064-r": 35,
        "sv6a-047-064-u": 160,
        "sv6a-048-064-c": 160,
        "sv6a-049-064-c": 160,
        "sv6a-050-064-c": 18,
        "sv6a-051-064-c": 160,
        "sv6a-052-064-c": 160,
        "sv6a-053-064-c": 160,
        "sv6a-054-064-ace": 160,
        "sv6a-055-064-ace": 160,
        "sv6a-056-064-u": 100,
        "sv6a-057-064-u": 33,
        "sv6a-058-064-u": 90,
        "sv6a-059-064-u": 99,
        "sv6a-060-064-u": 160,
        "sv6a-062-064-u": 160,
        "sv6a-063-064-ace": 160,
        "sv6a-064-064-u": 50,
        "sv6a-065-064-ar": 380,
        "sv6a-066-064-ar": 590,
        "sv6a-067-064-ar": 780,
        "sv6a-068-064-ar": 880,
        "sv6a-069-064-ar": 980,
        "sv6a-070-064-ar": 980,
        "sv6a-071-064-ar": 480,
        "sv6a-072-064-ar": 680,
        "sv6a-073-064-ar": 480,
        "sv6a-074-064-ar": 480,
        "sv6a-075-064-ar": 1280,
        "sv6a-076-064-ar": 480,
        "sv6a-077-064-sr": 320,
        "sv6a-078-064-sr": 380,
        "sv6a-079-064-sr": 380,
        "sv6a-080-064-sr": 380,
        "sv6a-081-064-sr": 1580,
        "sv6a-082-064-sr": 480,
        "sv6a-083-064-sr": 980,
        "sv6a-084-064-sr": 780,
        "sv6a-085-064-sr": 680,
        "sv6a-086-064-sr": 300,
        "sv6a-087-064-sar": 980,
        "sv6a-088-064-sar": 1080,
        "sv6a-089-064-sar": 4280,
        "sv6a-090-064-sar": 930,
        "sv6a-091-064-sar": 3280,
        "sv6a-092-064-ur": 780,
        "sv6a-093-064-ur": 980,
        "sv6a-094-064-ur": 920
      }
    },
    {
      "date": "2026-07-07",
      "prices": {
        "sv6a-001-064-c": 160,
        "sv6a-002-064-u": 18,
        "sv6a-003-064-c": 19,
        "sv6a-004-064-c": 160,
        "sv6a-005-064-u": 19,
        "sv6a-007-064-c": 160,
        "sv6a-008-064-c": 160,
        "sv6a-009-064-u": 160,
        "sv6a-010-064-c": 160,
        "sv6a-011-064-c": 160,
        "sv6a-014-064-u": 160,
        "sv6a-016-064-c": 160,
        "sv6a-017-064-u": 160,
        "sv6a-018-064-c": 160,
        "sv6a-019-064-c": 160,
        "sv6a-020-064-r": 160,
        "sv6a-021-064-r": 160,
        "sv6a-022-064-u": 19,
        "sv6a-023-064-c": 160,
        "sv6a-024-064-c": 160,
        "sv6a-025-064-r": 160,
        "sv6a-027-064-c": 160,
        "sv6a-028-064-c": 160,
        "sv6a-030-064-c": 160,
        "sv6a-033-064-c": 160,
        "sv6a-034-064-u": 160,
        "sv6a-036-064-rr": 160,
        "sv6a-038-064-rr": 180,
        "sv6a-040-064-u": 35,
        "sv6a-041-064-c": 160,
        "sv6a-042-064-r": 35,
        "sv6a-043-064-c": 160,
        "sv6a-044-064-c": 160,
        "sv6a-045-064-c": 160,
        "sv6a-047-064-u": 160,
        "sv6a-048-064-c": 160,
        "sv6a-050-064-c": 18,
        "sv6a-051-064-c": 160,
        "sv6a-052-064-c": 160,
        "sv6a-053-064-c": 160,
        "sv6a-054-064-ace": 160,
        "sv6a-055-064-ace": 160,
        "sv6a-056-064-u": 100,
        "sv6a-057-064-u": 33,
        "sv6a-058-064-u": 90,
        "sv6a-059-064-u": 99,
        "sv6a-060-064-u": 160,
        "sv6a-062-064-u": 160,
        "sv6a-063-064-ace": 160,
        "sv6a-065-064-ar": 380,
        "sv6a-066-064-ar": 590,
        "sv6a-067-064-ar": 780,
        "sv6a-068-064-ar": 880,
        "sv6a-069-064-ar": 980,
        "sv6a-070-064-ar": 980,
        "sv6a-071-064-ar": 480,
        "sv6a-072-064-ar": 680,
        "sv6a-073-064-ar": 480,
        "sv6a-074-064-ar": 480,
        "sv6a-075-064-ar": 1280,
        "sv6a-076-064-ar": 480,
        "sv6a-077-064-sr": 480,
        "sv6a-078-064-sr": 380,
        "sv6a-080-064-sr": 380,
        "sv6a-081-064-sr": 1580,
        "sv6a-082-064-sr": 480,
        "sv6a-083-064-sr": 980,
        "sv6a-084-064-sr": 780,
        "sv6a-085-064-sr": 680,
        "sv6a-086-064-sr": 300,
        "sv6a-087-064-sar": 980,
        "sv6a-088-064-sar": 1080,
        "sv6a-089-064-sar": 4280,
        "sv6a-090-064-sar": 930,
        "sv6a-091-064-sar": 3280,
        "sv6a-092-064-ur": 780,
        "sv6a-093-064-ur": 980,
        "sv6a-094-064-ur": 920
      }
    },
    {
      "date": "2026-07-08",
      "prices": {
        "sv6a-001-064-c": 160,
        "sv6a-002-064-u": 18,
        "sv6a-003-064-c": 19,
        "sv6a-004-064-c": 160,
        "sv6a-005-064-u": 19,
        "sv6a-006-064-r": 160,
        "sv6a-007-064-c": 160,
        "sv6a-008-064-c": 160,
        "sv6a-009-064-u": 160,
        "sv6a-010-064-c": 160,
        "sv6a-011-064-c": 160,
        "sv6a-012-064-rr": 160,
        "sv6a-013-064-c": 160,
        "sv6a-014-064-u": 160,
        "sv6a-015-064-rr": 160,
        "sv6a-016-064-c": 160,
        "sv6a-017-064-u": 160,
        "sv6a-018-064-c": 160,
        "sv6a-019-064-c": 160,
        "sv6a-020-064-r": 160,
        "sv6a-021-064-r": 160,
        "sv6a-022-064-u": 19,
        "sv6a-023-064-c": 160,
        "sv6a-024-064-c": 160,
        "sv6a-025-064-r": 160,
        "sv6a-026-064-u": 160,
        "sv6a-027-064-c": 160,
        "sv6a-028-064-c": 160,
        "sv6a-029-064-u": 160,
        "sv6a-030-064-c": 160,
        "sv6a-031-064-c": 160,
        "sv6a-032-064-r": 160,
        "sv6a-033-064-c": 160,
        "sv6a-034-064-u": 160,
        "sv6a-035-064-u": 160,
        "sv6a-036-064-rr": 160,
        "sv6a-037-064-rr": 160,
        "sv6a-038-064-rr": 180,
        "sv6a-039-064-rr": 160,
        "sv6a-040-064-u": 35,
        "sv6a-041-064-c": 160,
        "sv6a-042-064-r": 35,
        "sv6a-043-064-c": 160,
        "sv6a-044-064-c": 160,
        "sv6a-045-064-c": 160,
        "sv6a-046-064-r": 35,
        "sv6a-047-064-u": 160,
        "sv6a-048-064-c": 160,
        "sv6a-049-064-c": 160,
        "sv6a-050-064-c": 18,
        "sv6a-051-064-c": 160,
        "sv6a-052-064-c": 160,
        "sv6a-053-064-c": 160,
        "sv6a-054-064-ace": 160,
        "sv6a-055-064-ace": 160,
        "sv6a-056-064-u": 100,
        "sv6a-057-064-u": 33,
        "sv6a-058-064-u": 150,
        "sv6a-059-064-u": 99,
        "sv6a-060-064-u": 160,
        "sv6a-062-064-u": 160,
        "sv6a-063-064-ace": 160,
        "sv6a-064-064-u": 50,
        "sv6a-065-064-ar": 380,
        "sv6a-066-064-ar": 590,
        "sv6a-067-064-ar": 780,
        "sv6a-068-064-ar": 880,
        "sv6a-069-064-ar": 980,
        "sv6a-070-064-ar": 980,
        "sv6a-071-064-ar": 480,
        "sv6a-072-064-ar": 680,
        "sv6a-073-064-ar": 480,
        "sv6a-074-064-ar": 480,
        "sv6a-075-064-ar": 1280,
        "sv6a-076-064-ar": 480,
        "sv6a-077-064-sr": 480,
        "sv6a-078-064-sr": 380,
        "sv6a-079-064-sr": 380,
        "sv6a-080-064-sr": 380,
        "sv6a-081-064-sr": 1580,
        "sv6a-082-064-sr": 480,
        "sv6a-083-064-sr": 980,
        "sv6a-084-064-sr": 780,
        "sv6a-085-064-sr": 680,
        "sv6a-086-064-sr": 300,
        "sv6a-087-064-sar": 980,
        "sv6a-088-064-sar": 1080,
        "sv6a-089-064-sar": 4280,
        "sv6a-090-064-sar": 930,
        "sv6a-091-064-sar": 3280,
        "sv6a-092-064-ur": 780,
        "sv6a-093-064-ur": 980,
        "sv6a-094-064-ur": 920
      }
    },
    {
      "date": "2026-07-09",
      "prices": {
        "sv6a-001-064-c": 160,
        "sv6a-002-064-u": 18,
        "sv6a-003-064-c": 19,
        "sv6a-004-064-c": 160,
        "sv6a-005-064-u": 19,
        "sv6a-006-064-r": 160,
        "sv6a-007-064-c": 160,
        "sv6a-008-064-c": 160,
        "sv6a-009-064-u": 160,
        "sv6a-010-064-c": 160,
        "sv6a-011-064-c": 160,
        "sv6a-012-064-rr": 160,
        "sv6a-013-064-c": 160,
        "sv6a-014-064-u": 160,
        "sv6a-015-064-rr": 160,
        "sv6a-016-064-c": 160,
        "sv6a-017-064-u": 160,
        "sv6a-018-064-c": 160,
        "sv6a-019-064-c": 160,
        "sv6a-020-064-r": 160,
        "sv6a-021-064-r": 160,
        "sv6a-022-064-u": 19,
        "sv6a-023-064-c": 160,
        "sv6a-024-064-c": 160,
        "sv6a-025-064-r": 160,
        "sv6a-026-064-u": 160,
        "sv6a-027-064-c": 160,
        "sv6a-028-064-c": 160,
        "sv6a-029-064-u": 160,
        "sv6a-030-064-c": 160,
        "sv6a-031-064-c": 160,
        "sv6a-032-064-r": 160,
        "sv6a-033-064-c": 160,
        "sv6a-034-064-u": 160,
        "sv6a-035-064-u": 160,
        "sv6a-036-064-rr": 160,
        "sv6a-037-064-rr": 160,
        "sv6a-038-064-rr": 180,
        "sv6a-039-064-rr": 160,
        "sv6a-040-064-u": 35,
        "sv6a-041-064-c": 160,
        "sv6a-042-064-r": 35,
        "sv6a-043-064-c": 160,
        "sv6a-044-064-c": 160,
        "sv6a-045-064-c": 160,
        "sv6a-046-064-r": 35,
        "sv6a-047-064-u": 160,
        "sv6a-048-064-c": 160,
        "sv6a-049-064-c": 160,
        "sv6a-050-064-c": 18,
        "sv6a-051-064-c": 160,
        "sv6a-052-064-c": 160,
        "sv6a-053-064-c": 160,
        "sv6a-054-064-ace": 160,
        "sv6a-055-064-ace": 160,
        "sv6a-056-064-u": 100,
        "sv6a-057-064-u": 33,
        "sv6a-058-064-u": 150,
        "sv6a-059-064-u": 99,
        "sv6a-060-064-u": 160,
        "sv6a-062-064-u": 160,
        "sv6a-063-064-ace": 160,
        "sv6a-064-064-u": 50,
        "sv6a-065-064-ar": 380,
        "sv6a-066-064-ar": 590,
        "sv6a-067-064-ar": 780,
        "sv6a-068-064-ar": 410,
        "sv6a-069-064-ar": 980,
        "sv6a-070-064-ar": 980,
        "sv6a-071-064-ar": 480,
        "sv6a-072-064-ar": 680,
        "sv6a-073-064-ar": 480,
        "sv6a-074-064-ar": 480,
        "sv6a-075-064-ar": 1280,
        "sv6a-076-064-ar": 480,
        "sv6a-077-064-sr": 480,
        "sv6a-078-064-sr": 380,
        "sv6a-079-064-sr": 380,
        "sv6a-080-064-sr": 380,
        "sv6a-081-064-sr": 1580,
        "sv6a-082-064-sr": 480,
        "sv6a-083-064-sr": 980,
        "sv6a-084-064-sr": 780,
        "sv6a-085-064-sr": 680,
        "sv6a-086-064-sr": 300,
        "sv6a-087-064-sar": 980,
        "sv6a-088-064-sar": 1080,
        "sv6a-089-064-sar": 4280,
        "sv6a-090-064-sar": 930,
        "sv6a-091-064-sar": 3280,
        "sv6a-092-064-ur": 780,
        "sv6a-093-064-ur": 980,
        "sv6a-094-064-ur": 920
      }
    },
    {
      "date": "2026-07-10",
      "prices": {
        "sv6a-001-064-c": 160,
        "sv6a-002-064-u": 18,
        "sv6a-003-064-c": 19,
        "sv6a-004-064-c": 160,
        "sv6a-005-064-u": 19,
        "sv6a-006-064-r": 160,
        "sv6a-007-064-c": 160,
        "sv6a-008-064-c": 160,
        "sv6a-009-064-u": 160,
        "sv6a-010-064-c": 160,
        "sv6a-011-064-c": 160,
        "sv6a-012-064-rr": 160,
        "sv6a-013-064-c": 160,
        "sv6a-014-064-u": 160,
        "sv6a-015-064-rr": 160,
        "sv6a-016-064-c": 160,
        "sv6a-017-064-u": 160,
        "sv6a-018-064-c": 160,
        "sv6a-019-064-c": 160,
        "sv6a-020-064-r": 160,
        "sv6a-021-064-r": 160,
        "sv6a-022-064-u": 19,
        "sv6a-023-064-c": 160,
        "sv6a-024-064-c": 160,
        "sv6a-025-064-r": 160,
        "sv6a-026-064-u": 160,
        "sv6a-027-064-c": 160,
        "sv6a-028-064-c": 160,
        "sv6a-029-064-u": 160,
        "sv6a-030-064-c": 160,
        "sv6a-031-064-c": 160,
        "sv6a-032-064-r": 160,
        "sv6a-033-064-c": 160,
        "sv6a-034-064-u": 160,
        "sv6a-035-064-u": 160,
        "sv6a-036-064-rr": 160,
        "sv6a-037-064-rr": 160,
        "sv6a-038-064-rr": 180,
        "sv6a-039-064-rr": 160,
        "sv6a-040-064-u": 35,
        "sv6a-041-064-c": 160,
        "sv6a-042-064-r": 35,
        "sv6a-043-064-c": 160,
        "sv6a-044-064-c": 160,
        "sv6a-045-064-c": 160,
        "sv6a-046-064-r": 35,
        "sv6a-047-064-u": 160,
        "sv6a-048-064-c": 160,
        "sv6a-049-064-c": 160,
        "sv6a-050-064-c": 18,
        "sv6a-051-064-c": 160,
        "sv6a-052-064-c": 160,
        "sv6a-053-064-c": 160,
        "sv6a-054-064-ace": 160,
        "sv6a-055-064-ace": 160,
        "sv6a-056-064-u": 100,
        "sv6a-057-064-u": 33,
        "sv6a-058-064-u": 150,
        "sv6a-059-064-u": 99,
        "sv6a-060-064-u": 160,
        "sv6a-062-064-u": 160,
        "sv6a-063-064-ace": 160,
        "sv6a-064-064-u": 50,
        "sv6a-065-064-ar": 380,
        "sv6a-066-064-ar": 590,
        "sv6a-067-064-ar": 780,
        "sv6a-068-064-ar": 410,
        "sv6a-069-064-ar": 980,
        "sv6a-070-064-ar": 980,
        "sv6a-071-064-ar": 480,
        "sv6a-072-064-ar": 680,
        "sv6a-073-064-ar": 480,
        "sv6a-074-064-ar": 480,
        "sv6a-075-064-ar": 1280,
        "sv6a-076-064-ar": 480,
        "sv6a-077-064-sr": 480,
        "sv6a-078-064-sr": 380,
        "sv6a-079-064-sr": 380,
        "sv6a-080-064-sr": 380,
        "sv6a-081-064-sr": 1580,
        "sv6a-082-064-sr": 480,
        "sv6a-083-064-sr": 980,
        "sv6a-084-064-sr": 780,
        "sv6a-085-064-sr": 680,
        "sv6a-086-064-sr": 300,
        "sv6a-087-064-sar": 980,
        "sv6a-088-064-sar": 1080,
        "sv6a-089-064-sar": 4280,
        "sv6a-090-064-sar": 930,
        "sv6a-091-064-sar": 3280,
        "sv6a-092-064-ur": 780,
        "sv6a-093-064-ur": 980,
        "sv6a-094-064-ur": 920
      }
    },
    {
      "date": "2026-07-11",
      "prices": {
        "sv6a-001-064-c": 160,
        "sv6a-002-064-u": 18,
        "sv6a-003-064-c": 19,
        "sv6a-004-064-c": 160,
        "sv6a-005-064-u": 19,
        "sv6a-006-064-r": 160,
        "sv6a-007-064-c": 160,
        "sv6a-008-064-c": 160,
        "sv6a-009-064-u": 160,
        "sv6a-010-064-c": 160,
        "sv6a-011-064-c": 160,
        "sv6a-012-064-rr": 160,
        "sv6a-013-064-c": 160,
        "sv6a-014-064-u": 160,
        "sv6a-015-064-rr": 160,
        "sv6a-016-064-c": 160,
        "sv6a-017-064-u": 160,
        "sv6a-018-064-c": 160,
        "sv6a-019-064-c": 160,
        "sv6a-020-064-r": 160,
        "sv6a-021-064-r": 160,
        "sv6a-022-064-u": 19,
        "sv6a-023-064-c": 160,
        "sv6a-024-064-c": 160,
        "sv6a-025-064-r": 160,
        "sv6a-026-064-u": 160,
        "sv6a-027-064-c": 160,
        "sv6a-028-064-c": 160,
        "sv6a-029-064-u": 160,
        "sv6a-030-064-c": 160,
        "sv6a-031-064-c": 160,
        "sv6a-032-064-r": 160,
        "sv6a-033-064-c": 160,
        "sv6a-034-064-u": 160,
        "sv6a-035-064-u": 160,
        "sv6a-036-064-rr": 160,
        "sv6a-037-064-rr": 160,
        "sv6a-038-064-rr": 180,
        "sv6a-039-064-rr": 160,
        "sv6a-040-064-u": 35,
        "sv6a-041-064-c": 160,
        "sv6a-042-064-r": 35,
        "sv6a-043-064-c": 160,
        "sv6a-044-064-c": 160,
        "sv6a-045-064-c": 160,
        "sv6a-046-064-r": 35,
        "sv6a-047-064-u": 160,
        "sv6a-048-064-c": 160,
        "sv6a-049-064-c": 160,
        "sv6a-050-064-c": 18,
        "sv6a-051-064-c": 160,
        "sv6a-052-064-c": 160,
        "sv6a-053-064-c": 160,
        "sv6a-054-064-ace": 160,
        "sv6a-055-064-ace": 160,
        "sv6a-056-064-u": 100,
        "sv6a-057-064-u": 33,
        "sv6a-058-064-u": 90,
        "sv6a-059-064-u": 60,
        "sv6a-060-064-u": 160,
        "sv6a-062-064-u": 160,
        "sv6a-063-064-ace": 160,
        "sv6a-064-064-u": 50,
        "sv6a-065-064-ar": 340,
        "sv6a-066-064-ar": 590,
        "sv6a-067-064-ar": 780,
        "sv6a-068-064-ar": 880,
        "sv6a-069-064-ar": 980,
        "sv6a-070-064-ar": 980,
        "sv6a-071-064-ar": 480,
        "sv6a-072-064-ar": 680,
        "sv6a-073-064-ar": 480,
        "sv6a-074-064-ar": 480,
        "sv6a-075-064-ar": 1280,
        "sv6a-076-064-ar": 430,
        "sv6a-077-064-sr": 480,
        "sv6a-078-064-sr": 380,
        "sv6a-079-064-sr": 380,
        "sv6a-080-064-sr": 380,
        "sv6a-081-064-sr": 1580,
        "sv6a-082-064-sr": 480,
        "sv6a-083-064-sr": 980,
        "sv6a-084-064-sr": 780,
        "sv6a-085-064-sr": 680,
        "sv6a-086-064-sr": 300,
        "sv6a-087-064-sar": 980,
        "sv6a-088-064-sar": 1080,
        "sv6a-089-064-sar": 4280,
        "sv6a-090-064-sar": 930,
        "sv6a-091-064-sar": 3280,
        "sv6a-092-064-ur": 780,
        "sv6a-093-064-ur": 980,
        "sv6a-094-064-ur": 920
      }
    },
    {
      "date": "2026-07-12",
      "prices": {
        "sv6a-001-064-c": 160,
        "sv6a-002-064-u": 18,
        "sv6a-003-064-c": 19,
        "sv6a-004-064-c": 160,
        "sv6a-005-064-u": 19,
        "sv6a-006-064-r": 160,
        "sv6a-007-064-c": 160,
        "sv6a-008-064-c": 160,
        "sv6a-009-064-u": 160,
        "sv6a-010-064-c": 160,
        "sv6a-011-064-c": 160,
        "sv6a-012-064-rr": 160,
        "sv6a-013-064-c": 160,
        "sv6a-014-064-u": 160,
        "sv6a-015-064-rr": 160,
        "sv6a-016-064-c": 160,
        "sv6a-017-064-u": 160,
        "sv6a-018-064-c": 160,
        "sv6a-019-064-c": 160,
        "sv6a-020-064-r": 160,
        "sv6a-021-064-r": 160,
        "sv6a-022-064-u": 19,
        "sv6a-023-064-c": 160,
        "sv6a-024-064-c": 160,
        "sv6a-025-064-r": 160,
        "sv6a-026-064-u": 160,
        "sv6a-027-064-c": 160,
        "sv6a-028-064-c": 160,
        "sv6a-029-064-u": 160,
        "sv6a-030-064-c": 160,
        "sv6a-031-064-c": 160,
        "sv6a-032-064-r": 160,
        "sv6a-033-064-c": 160,
        "sv6a-034-064-u": 160,
        "sv6a-035-064-u": 160,
        "sv6a-036-064-rr": 160,
        "sv6a-037-064-rr": 160,
        "sv6a-038-064-rr": 180,
        "sv6a-039-064-rr": 160,
        "sv6a-040-064-u": 35,
        "sv6a-041-064-c": 160,
        "sv6a-042-064-r": 35,
        "sv6a-043-064-c": 160,
        "sv6a-044-064-c": 160,
        "sv6a-045-064-c": 160,
        "sv6a-046-064-r": 35,
        "sv6a-047-064-u": 160,
        "sv6a-048-064-c": 160,
        "sv6a-049-064-c": 160,
        "sv6a-050-064-c": 18,
        "sv6a-051-064-c": 160,
        "sv6a-052-064-c": 160,
        "sv6a-053-064-c": 160,
        "sv6a-054-064-ace": 160,
        "sv6a-055-064-ace": 160,
        "sv6a-056-064-u": 100,
        "sv6a-057-064-u": 33,
        "sv6a-058-064-u": 90,
        "sv6a-059-064-u": 60,
        "sv6a-060-064-u": 160,
        "sv6a-062-064-u": 160,
        "sv6a-063-064-ace": 160,
        "sv6a-064-064-u": 50,
        "sv6a-065-064-ar": 380,
        "sv6a-066-064-ar": 590,
        "sv6a-067-064-ar": 780,
        "sv6a-068-064-ar": 880,
        "sv6a-069-064-ar": 980,
        "sv6a-070-064-ar": 980,
        "sv6a-071-064-ar": 480,
        "sv6a-072-064-ar": 680,
        "sv6a-073-064-ar": 480,
        "sv6a-074-064-ar": 480,
        "sv6a-075-064-ar": 1280,
        "sv6a-076-064-ar": 480,
        "sv6a-077-064-sr": 480,
        "sv6a-078-064-sr": 380,
        "sv6a-079-064-sr": 380,
        "sv6a-080-064-sr": 380,
        "sv6a-081-064-sr": 1580,
        "sv6a-082-064-sr": 480,
        "sv6a-083-064-sr": 980,
        "sv6a-084-064-sr": 780,
        "sv6a-085-064-sr": 680,
        "sv6a-086-064-sr": 300,
        "sv6a-087-064-sar": 980,
        "sv6a-088-064-sar": 1080,
        "sv6a-089-064-sar": 4280,
        "sv6a-090-064-sar": 930,
        "sv6a-091-064-sar": 3280,
        "sv6a-092-064-ur": 780,
        "sv6a-093-064-ur": 980,
        "sv6a-094-064-ur": 920
      }
    },
    {
      "date": "2026-07-14",
      "prices": {
        "sv6a-001-064-c": 160,
        "sv6a-002-064-u": 18,
        "sv6a-003-064-c": 19,
        "sv6a-004-064-c": 160,
        "sv6a-005-064-u": 19,
        "sv6a-006-064-r": 160,
        "sv6a-007-064-c": 160,
        "sv6a-008-064-c": 160,
        "sv6a-009-064-u": 160,
        "sv6a-010-064-c": 160,
        "sv6a-011-064-c": 160,
        "sv6a-012-064-rr": 160,
        "sv6a-013-064-c": 160,
        "sv6a-014-064-u": 160,
        "sv6a-015-064-rr": 160,
        "sv6a-016-064-c": 160,
        "sv6a-017-064-u": 160,
        "sv6a-018-064-c": 160,
        "sv6a-019-064-c": 160,
        "sv6a-020-064-r": 160,
        "sv6a-021-064-r": 160,
        "sv6a-022-064-u": 19,
        "sv6a-023-064-c": 160,
        "sv6a-024-064-c": 160,
        "sv6a-025-064-r": 160,
        "sv6a-026-064-u": 160,
        "sv6a-027-064-c": 160,
        "sv6a-028-064-c": 160,
        "sv6a-029-064-u": 160,
        "sv6a-030-064-c": 160,
        "sv6a-031-064-c": 160,
        "sv6a-032-064-r": 160,
        "sv6a-033-064-c": 160,
        "sv6a-034-064-u": 160,
        "sv6a-035-064-u": 160,
        "sv6a-036-064-rr": 160,
        "sv6a-037-064-rr": 160,
        "sv6a-038-064-rr": 180,
        "sv6a-039-064-rr": 160,
        "sv6a-040-064-u": 35,
        "sv6a-041-064-c": 160,
        "sv6a-042-064-r": 35,
        "sv6a-043-064-c": 160,
        "sv6a-044-064-c": 160,
        "sv6a-045-064-c": 160,
        "sv6a-046-064-r": 35,
        "sv6a-047-064-u": 160,
        "sv6a-048-064-c": 160,
        "sv6a-049-064-c": 160,
        "sv6a-050-064-c": 19,
        "sv6a-051-064-c": 160,
        "sv6a-052-064-c": 160,
        "sv6a-053-064-c": 160,
        "sv6a-054-064-ace": 160,
        "sv6a-055-064-ace": 160,
        "sv6a-056-064-u": 100,
        "sv6a-057-064-u": 31,
        "sv6a-058-064-u": 150,
        "sv6a-059-064-u": 99,
        "sv6a-060-064-u": 160,
        "sv6a-062-064-u": 160,
        "sv6a-063-064-ace": 160,
        "sv6a-064-064-u": 50,
        "sv6a-065-064-ar": 380,
        "sv6a-066-064-ar": 590,
        "sv6a-067-064-ar": 780,
        "sv6a-068-064-ar": 880,
        "sv6a-069-064-ar": 980,
        "sv6a-070-064-ar": 980,
        "sv6a-071-064-ar": 480,
        "sv6a-072-064-ar": 680,
        "sv6a-073-064-ar": 480,
        "sv6a-074-064-ar": 480,
        "sv6a-075-064-ar": 1280,
        "sv6a-076-064-ar": 480,
        "sv6a-077-064-sr": 480,
        "sv6a-078-064-sr": 380,
        "sv6a-079-064-sr": 380,
        "sv6a-080-064-sr": 380,
        "sv6a-081-064-sr": 1580,
        "sv6a-082-064-sr": 480,
        "sv6a-083-064-sr": 980,
        "sv6a-084-064-sr": 780,
        "sv6a-085-064-sr": 680,
        "sv6a-086-064-sr": 300,
        "sv6a-087-064-sar": 980,
        "sv6a-088-064-sar": 1080,
        "sv6a-089-064-sar": 4280,
        "sv6a-090-064-sar": 630,
        "sv6a-091-064-sar": 3280,
        "sv6a-092-064-ur": 780,
        "sv6a-093-064-ur": 980,
        "sv6a-094-064-ur": 920
      }
    },
    {
      "date": "2026-07-15",
      "prices": {
        "sv6a-001-064-c": 160,
        "sv6a-002-064-u": 18,
        "sv6a-003-064-c": 19,
        "sv6a-004-064-c": 160,
        "sv6a-005-064-u": 19,
        "sv6a-006-064-r": 160,
        "sv6a-007-064-c": 160,
        "sv6a-008-064-c": 160,
        "sv6a-009-064-u": 160,
        "sv6a-010-064-c": 160,
        "sv6a-011-064-c": 160,
        "sv6a-012-064-rr": 160,
        "sv6a-013-064-c": 160,
        "sv6a-014-064-u": 160,
        "sv6a-015-064-rr": 160,
        "sv6a-016-064-c": 160,
        "sv6a-017-064-u": 160,
        "sv6a-018-064-c": 160,
        "sv6a-019-064-c": 160,
        "sv6a-020-064-r": 160,
        "sv6a-021-064-r": 160,
        "sv6a-022-064-u": 19,
        "sv6a-023-064-c": 160,
        "sv6a-024-064-c": 160,
        "sv6a-025-064-r": 160,
        "sv6a-026-064-u": 160,
        "sv6a-027-064-c": 160,
        "sv6a-028-064-c": 160,
        "sv6a-029-064-u": 160,
        "sv6a-030-064-c": 160,
        "sv6a-031-064-c": 160,
        "sv6a-032-064-r": 160,
        "sv6a-033-064-c": 160,
        "sv6a-034-064-u": 160,
        "sv6a-035-064-u": 19,
        "sv6a-036-064-rr": 160,
        "sv6a-037-064-rr": 160,
        "sv6a-038-064-rr": 180,
        "sv6a-039-064-rr": 160,
        "sv6a-040-064-u": 35,
        "sv6a-041-064-c": 160,
        "sv6a-042-064-r": 35,
        "sv6a-043-064-c": 160,
        "sv6a-044-064-c": 160,
        "sv6a-045-064-c": 160,
        "sv6a-046-064-r": 35,
        "sv6a-047-064-u": 160,
        "sv6a-048-064-c": 160,
        "sv6a-049-064-c": 160,
        "sv6a-050-064-c": 19,
        "sv6a-051-064-c": 160,
        "sv6a-052-064-c": 160,
        "sv6a-053-064-c": 160,
        "sv6a-054-064-ace": 160,
        "sv6a-055-064-ace": 160,
        "sv6a-056-064-u": 100,
        "sv6a-057-064-u": 31,
        "sv6a-058-064-u": 150,
        "sv6a-059-064-u": 99,
        "sv6a-060-064-u": 160,
        "sv6a-062-064-u": 160,
        "sv6a-063-064-ace": 160,
        "sv6a-064-064-u": 50,
        "sv6a-065-064-ar": 380,
        "sv6a-066-064-ar": 590,
        "sv6a-067-064-ar": 780,
        "sv6a-068-064-ar": 880,
        "sv6a-069-064-ar": 980,
        "sv6a-070-064-ar": 980,
        "sv6a-071-064-ar": 480,
        "sv6a-072-064-ar": 680,
        "sv6a-073-064-ar": 480,
        "sv6a-074-064-ar": 480,
        "sv6a-075-064-ar": 1280,
        "sv6a-076-064-ar": 480,
        "sv6a-077-064-sr": 480,
        "sv6a-078-064-sr": 380,
        "sv6a-079-064-sr": 380,
        "sv6a-080-064-sr": 380,
        "sv6a-081-064-sr": 1580,
        "sv6a-082-064-sr": 480,
        "sv6a-083-064-sr": 980,
        "sv6a-084-064-sr": 780,
        "sv6a-085-064-sr": 680,
        "sv6a-086-064-sr": 300,
        "sv6a-087-064-sar": 980,
        "sv6a-088-064-sar": 1080,
        "sv6a-089-064-sar": 4280,
        "sv6a-090-064-sar": 630,
        "sv6a-091-064-sar": 3280,
        "sv6a-092-064-ur": 780,
        "sv6a-093-064-ur": 980,
        "sv6a-094-064-ur": 670
      }
    },
    {
      "date": "2026-07-16",
      "prices": {
        "sv6a-001-064-c": 160,
        "sv6a-002-064-u": 18,
        "sv6a-003-064-c": 19,
        "sv6a-004-064-c": 160,
        "sv6a-005-064-u": 19,
        "sv6a-006-064-r": 160,
        "sv6a-007-064-c": 160,
        "sv6a-008-064-c": 160,
        "sv6a-009-064-u": 160,
        "sv6a-010-064-c": 160,
        "sv6a-011-064-c": 160,
        "sv6a-012-064-rr": 160,
        "sv6a-013-064-c": 160,
        "sv6a-014-064-u": 160,
        "sv6a-015-064-rr": 160,
        "sv6a-016-064-c": 160,
        "sv6a-017-064-u": 160,
        "sv6a-018-064-c": 160,
        "sv6a-019-064-c": 160,
        "sv6a-020-064-r": 160,
        "sv6a-021-064-r": 160,
        "sv6a-022-064-u": 19,
        "sv6a-023-064-c": 160,
        "sv6a-024-064-c": 160,
        "sv6a-025-064-r": 160,
        "sv6a-026-064-u": 160,
        "sv6a-027-064-c": 160,
        "sv6a-028-064-c": 160,
        "sv6a-029-064-u": 160,
        "sv6a-030-064-c": 160,
        "sv6a-031-064-c": 160,
        "sv6a-032-064-r": 160,
        "sv6a-033-064-c": 160,
        "sv6a-034-064-u": 160,
        "sv6a-035-064-u": 19,
        "sv6a-036-064-rr": 160,
        "sv6a-037-064-rr": 160,
        "sv6a-038-064-rr": 180,
        "sv6a-039-064-rr": 160,
        "sv6a-040-064-u": 35,
        "sv6a-041-064-c": 160,
        "sv6a-042-064-r": 35,
        "sv6a-043-064-c": 160,
        "sv6a-044-064-c": 160,
        "sv6a-045-064-c": 160,
        "sv6a-046-064-r": 35,
        "sv6a-047-064-u": 160,
        "sv6a-048-064-c": 160,
        "sv6a-049-064-c": 160,
        "sv6a-050-064-c": 19,
        "sv6a-051-064-c": 160,
        "sv6a-052-064-c": 160,
        "sv6a-053-064-c": 160,
        "sv6a-054-064-ace": 160,
        "sv6a-055-064-ace": 160,
        "sv6a-056-064-u": 100,
        "sv6a-057-064-u": 31,
        "sv6a-058-064-u": 150,
        "sv6a-059-064-u": 99,
        "sv6a-060-064-u": 160,
        "sv6a-062-064-u": 160,
        "sv6a-063-064-ace": 160,
        "sv6a-064-064-u": 50,
        "sv6a-065-064-ar": 380,
        "sv6a-066-064-ar": 590,
        "sv6a-067-064-ar": 780,
        "sv6a-068-064-ar": 880,
        "sv6a-069-064-ar": 980,
        "sv6a-070-064-ar": 980,
        "sv6a-071-064-ar": 480,
        "sv6a-072-064-ar": 680,
        "sv6a-073-064-ar": 480,
        "sv6a-074-064-ar": 480,
        "sv6a-075-064-ar": 1280,
        "sv6a-076-064-ar": 480,
        "sv6a-077-064-sr": 480,
        "sv6a-078-064-sr": 380,
        "sv6a-079-064-sr": 380,
        "sv6a-080-064-sr": 380,
        "sv6a-081-064-sr": 1580,
        "sv6a-082-064-sr": 480,
        "sv6a-083-064-sr": 980,
        "sv6a-084-064-sr": 780,
        "sv6a-085-064-sr": 680,
        "sv6a-086-064-sr": 300,
        "sv6a-087-064-sar": 980,
        "sv6a-088-064-sar": 1080,
        "sv6a-089-064-sar": 4280,
        "sv6a-090-064-sar": 630,
        "sv6a-091-064-sar": 3280,
        "sv6a-092-064-ur": 780,
        "sv6a-093-064-ur": 980,
        "sv6a-094-064-ur": 670
      }
    }
  ]
}
